Latex_toolkit/__init__.py
Latex_toolkit/main.py
latex_toolkit-0.1.dist-info/METADATA
latex_toolkit-0.1.dist-info/WHEEL
latex_toolkit-0.1.dist-info/entry_points.txt
latex_toolkit-0.1.dist-info/top_level.txt
latex_toolkit-0.1.dist-info/RECORD
