Metadata-Version: 2.2
Name: Latex_toolkit
Version: 0.1
Dynamic: description
Dynamic: description-content-type
